Workbook

Sheet LISTADO DE PRECIOS
G1: CATEGORIA
A2: COD UPON | B2: Nombre Producto | D2: PRESENTACION 1 | E2: PRESENTACION 2 | F2: PRECIO VENTA MERCADOS | G2: % TIPO DE PROCION POR EL TOTAL VENDIDO DEL MES | H2: PROVINCIA 3% | I2: PRECIO DE VENTA PROVINCIAS | J2: DISTRIBUIDOS A 12% | K2: PRECIO DE VENTA DISTRIBUIDORES A | L2: DISTRIBUIDORES B 8% | M2: PRECIO DE VENTA DISTRIBUIDORES B | N2: DIVECO 25% | O2: PRECIO DE VENTA DIVECO | P2: PRECIO VENTA SUPERMERCADO | Q2: PRESENTACION SUPERMERCADO | R2: PRECIO UNITARIO SUPERMERCADO
A3: PTEX01007 | B3: BOOHOO CRUNCHY QUESO 40g (12 TIRAS/CAJA) | D3: CAJA | E3: TIRA | F3: 264 | G3: PROMOCIONAL | H3: =+F3*3% -> 7.92 | I3: =+F3+H3 -> 271.92 | J3: =+F3*12% -> 31.68 | K3: =+F3-J3 -> 232.32 | L3: =+F3*8% -> 21.12 | M3: =+F3-L3 -> 242.88 | N3: =+F3*25% -> 66 | O3: =+F3-N3 -> 198 | P3: 264 | Q3: 12 | R3: =+F3/Q3 -> 22
A4: PTEX01005 | B4: BOOHOO PUFF PICANTE 30g (6 TIRAS/jABA) | D4: JABA | E4: TIRA | F4: 91.8 | G4: PROMOCIONAL | H4: =+F4*3% -> 2.754 | I4: =+F4+H4 -> 94.554 | J4: =+F4*12% -> 11.016 | K4: =+F4-J4 -> 80.784 | L4: =+F4*8% -> 7.344 | M4: =+F4-L4 -> 84.456 | N4: =+F4*25% -> 22.95 | O4: =+F4-N4 -> 68.85 | P4: 91.8 | Q4: 6 | R4: =+F4/Q4 -> 15.3
A5: PTEX01004 | B5: BOOHOO PUFF QUESO 30g (6 TIRAS/jABA) | D5: JABA | E5: TIRA | F5: 91.8 | G5: PROMOCIONAL | H5: =+F5*3% -> 2.754 | I5: =+F5+H5 -> 94.554 | J5: =+F5*12% -> 11.016 | K5: =+F5-J5 -> 80.784 | L5: =+F5*8% -> 7.344 | M5: =+F5-L5 -> 84.456 | N5: =+F5*25% -> 22.95 | O5: =+F5-N5 -> 68.85 | P5: 91.8 | Q5: 6 | R5: =+F5/Q5 -> 15.3
A6: PTEX02001 | B6: BOOHOO QUESO 35g | D6: JABA | E6: TIRA | F6: 122.4 | G6: PROMOCIONAL | H6: =+F6*3% -> 3.672 | I6: =+F6+H6 -> 126.072 | J6: =+F6*12% -> 14.688 | K6: =+F6-J6 -> 107.712 | L6: =+F6*8% -> 9.792 | M6: =+F6-L6 -> 112.608 | N6: =+F6*25% -> 30.6 | O6: =+F6-N6 -> 91.8 | P6: 122.4 | Q6: 8 | R6: =+F6/Q6 -> 15.3
A7: PTEX01012 | B7: BOOHOO PUFF QUESO 120g (20 UNIDADES/JABA) | D7: JABA | E7: UND | F7: 128 | G7: PROMOCIONAL | H7: =+F7*3% -> 3.84 | I7: =+F7+H7 -> 131.84 | J7: =+F7*12% -> 15.36 | K7: =+F7-J7 -> 112.64 | L7: =+F7*8% -> 10.24 | M7: =+F7-L7 -> 117.76 | N7: =+F7*25% -> 32 | O7: =+F7-N7 -> 96 | P7: 128 | Q7: 20 | R7: =+F7/Q7 -> 6.4
A8: PTEX01013 | B8: BOOHOO PUFF PICANTE 120g (20 UNIDADES/JABA) | D8: JABA | E8: UND | F8: 128 | G8: PROMOCIONAL | H8: =+F8*3% -> 3.84 | I8: =+F8+H8 -> 131.84 | J8: =+F8*12% -> 15.36 | K8: =+F8-J8 -> 112.64 | L8: =+F8*8% -> 10.24 | M8: =+F8-L8 -> 117.76 | N8: =+F8*25% -> 32 | O8: =+F8-N8 -> 96 | P8: 128 | Q8: 20 | R8: =+F8/Q8 -> 6.4
A9: PTEX02003 | B9: BOOHOO NAX QUESO 150g (20u/JBA) | D9: JABA | E9: UND | F9: 128 | G9: PROMOCIONAL | H9: =+F9*3% -> 3.84 | I9: =+F9+H9 -> 131.84 | J9: =+F9*12% -> 15.36 | K9: =+F9-J9 -> 112.64 | L9: =+F9*8% -> 10.24 | M9: =+F9-L9 -> 117.76 | N9: =+F9*25% -> 32 | O9: =+F9-N9 -> 96 | P9: 128 | Q9: 20 | R9: =+F9/Q9 -> 6.4
A10: PTMA01001 | B10: ESCUELIN 12X60X25g JABA | D10: JABA | E10: CAJA | F10: 462 | G10: REGULAR | H10: =+F10*3% -> 13.86 | I10: =+F10+H10 -> 475.86 | J10: =+F10*12% -> 55.44 | K10: =+F10-J10 -> 406.56 | L10: =+F10*8% -> 36.96 | M10: =+F10-L10 -> 425.04 | N10: =+F10*25% -> 115.5 | O10: =+F10-N10 -> 346.5 | P10: 462 | Q10: 12 | R10: =+F10/Q10 -> 38.5
A11: PTMA01004 | B11: GALLETA CHIPS DE CHOCOLATE EN TIRAS (10 TIRAS X 10u 35g/CAJA) | D11: CAJA | E11: TIRA | F11: 155 | G11: PROMOCIONAL | H11: =+F11*3% -> 4.65 | I11: =+F11+H11 -> 159.65 | J11: =+F11*12% -> 18.6 | K11: =+F11-J11 -> 136.4 | L11: =+F11*8% -> 12.4 | M11: =+F11-L11 -> 142.6 | N11: =+F11*25% -> 38.75 | O11: =+F11-N11 -> 116.25 | P11: 155 | Q11: 10 | R11: =+F11/Q11 -> 15.5
A12: PTMA01002 | B12: MEGABLON 14g BOLSA | D12: CAJA | E12: BOLSA | F12: 240 | G12: REGULAR | H12: =+F12*3% -> 7.2 | I12: =+F12+H12 -> 247.2 | J12: =+F12*12% -> 28.8 | K12: =+F12-J12 -> 211.2 | L12: =+F12*8% -> 19.2 | M12: =+F12-L12 -> 220.8 | N12: =+F12*25% -> 60 | O12: =+F12-N12 -> 180 | P12: 240 | Q12: 16 | R12: =+F12/Q12 -> 15
A13: PTFR03004 | B13: MIX NAX 120g (20 bol/jba) | D13: CAJA | E13: UND | F13: 270 | G13: PROMOCIONAL | H13: =+F13*3% -> 8.1 | I13: =+F13+H13 -> 278.1 | J13: =+F13*12% -> 32.4 | K13: =+F13-J13 -> 237.6 | L13: =+F13*8% -> 21.6 | M13: =+F13-L13 -> 248.4 | N13: =+F13*25% -> 67.5 | O13: =+F13-N13 -> 202.5 | P13: 270 | Q13: 20 | R13: =+F13/Q13 -> 13.5
A14: PTFR03002 | B14: MIX NAX 45G | D14: CAJA | E14: TIRA | F14: 176 | G14: PROMOCIONAL | H14: =+F14*3% -> 5.28 | I14: =+F14+H14 -> 181.28 | J14: =+F14*12% -> 21.12 | K14: =+F14-J14 -> 154.88 | L14: =+F14*8% -> 14.08 | M14: =+F14-L14 -> 161.92 | N14: =+F14*25% -> 44 | O14: =+F14-N14 -> 132 | P14: 176 | Q14: 8 | R14: =+F14/Q14 -> 22
... A18: PTFR01014 | B18: NACHONAX LIMÓN 200g (20 BOL/CJA) | D18: CAJA | E18: UND | F18: 168 | G18: REGULAR | H18: =+F18*3% -> 5.04 | I18: =+F18+H18 -> 173.04 | J18: =+F18*12% -> 20.16 | K18: =+F18-J18 -> 147.84 | L18: =+F18*8% -> 13.44 | M18: =+F18-L18 -> 154.56 | N18: =+F18*25% -> 42 | O18: =+F18-N18 -> 126 | P18: 168 | Q18: 20 | R18: =+F18/Q18 -> 8.4
A19: PTFR03005 | B19: PACK SUPERMERCADO (Surtido Nacho, Papa, Boohoo: 6u) | D19: CAJA | E19: UND | P19: =10.5*15 -> 157.5 | Q19: 15 | R19: =+P19/Q19 -> 10.5
A20: PTFR01006 | B20: NACHONAX QUESO 200g | D20: CAJA | E20: UND | F20: 248 | G20: REGULAR | H20: =+F20*3% -> 7.44 | I20: =+F20+H20 -> 255.44 | J20: =+F20*12% -> 29.76 | K20: =+F20-J20 -> 218.24 | L20: =+F20*8% -> 19.84 | M20: =+F20-L20 -> 228.16 | N20: =+F20*25% -> 62 | O20: =+F20-N20 -> 186 | P20: 248 | Q20: 20 | R20: =+F20/Q20 -> 12.4
A21: PTFR01003 | B21: NACHONAX QUESO 45g tira | D21: CAJA | E21: TIRA | F21: 300 | G21: REGULAR | H21: =+F21*3% -> 9 | I21: =+F21+H21 -> 309 | J21: =+F21*12% -> 36 | K21: =+F21-J21 -> 264 | L21: =+F21*8% -> 24 | M21: =+F21-L21 -> 276 | N21: =+F21*25% -> 75 | O21: =+F21-N21 -> 225 | P21: 300 | Q21: 12 | R21: =+F21/Q21 -> 25
A22: PTFR01004 | B22: NACHONAX SALADO 200g | D22: CAJA | E22: UND | F22: 168 | G22: REGULAR | H22: =+F22*3% -> 5.04 | I22: =+F22+H22 -> 173.04 | J22: =+F22*12% -> 20.16 | K22: =+F22-J22 -> 147.84 | L22: =+F22*8% -> 13.44 | M22: =+F22-L22 -> 154.56 | N22: =+F22*25% -> 42 | O22: =+F22-N22 -> 126 | P22: 168 | Q22: 20 | R22: =+F22/Q22 -> 8.4
A23: PTFR01001 | B23: NACHONAX SALADO 45g tira | D23: CAJA | E23: TIRA | F23: 264 | G23: REGULAR | H23: =+F23*3% -> 7.92 | I23: =+F23+H23 -> 271.92 | J23: =+F23*12% -> 31.68 | K23: =+F23-J23 -> 232.32 | L23: =+F23*8% -> 21.12 | M23: =+F23-L23 -> 242.88 | N23: =+F23*25% -> 66 | O23: =+F23-N23 -> 198 | P23: 264 | Q23: 12 | R23: =+F23/Q23 -> 22
A24: PTFR02008 | B24: PAPANAX CHURRASCO 110g (30 BOLSAS/CAJA) | D24: CAJA | E24: UND | F24: 222 | G24: REGULAR | H24: =+F24*3% -> 6.66 | I24: =+F24+H24 -> 228.66 | J24: =+F24*12% -> 26.64 | K24: =+F24-J24 -> 195.36 | L24: =+F24*8% -> 17.76 | M24: =+F24-L24 -> 204.24 | N24: =+F24*25% -> 55.5 | O24: =+F24-N24 -> 166.5 | P24: 222 | Q24: 30 | R24: =+F24/Q24 -> 7.4
A25: PTFR02007 | B25: PAPANAX CHURRASCO 20g (12 TIRAS/CAJA) | D25: CAJA | E25: TIRA | F25: 240 | G25: REGULAR | H25: =+F25*3% -> 7.2 | I25: =+F25+H25 -> 247.2 | J25: =+F25*12% -> 28.8 | K25: =+F25-J25 -> 211.2 | L25: =+F25*8% -> 19.2 | M25: =+F25-L25 -> 220.8 | N25: =+F25*25% -> 60 | O25: =+F25-N25 -> 180 | P25: 240 | Q25: 12 | R25: =+F25/Q25 -> 20
A26: PTFR02006 | B26: PAPANAX EXTRA FUEGO 110g | D26: CAJA | E26: UND | F26: 222 | G26: REGULAR | H26: =+F26*3% -> 6.66 | I26: =+F26+H26 -> 228.66 | J26: =+F26*12% -> 26.64 | K26: =+F26-J26 -> 195.36 | L26: =+F26*8% -> 17.76 | M26: =+F26-L26 -> 204.24 | N26: =+F26*25% -> 55.5 | O26: =+F26-N26 -> 166.5 | P26: 222 | Q26: 30 | R26: =+F26/Q26 -> 7.4
A27: PTFR02003 | B27: PAPANAX EXTRA FUEGO 20g | D27: CAJA | E27: TIRA | F27: 240 | G27: REGULAR | H27: =+F27*3% -> 7.2 | I27: =+F27+H27 -> 247.2 | J27: =+F27*12% -> 28.8 | K27: =+F27-J27 -> 211.2 | L27: =+F27*8% -> 19.2 | M27: =+F27-L27 -> 220.8 | N27: =+F27*25% -> 60 | O27: =+F27-N27 -> 180 | P27: 240 | Q27: 12 | R27: =+F27/Q27 -> 20
A28: PTFR02002 | B28: PAPANAX PICANTE 20g | D28: CAJA | E28: TIRA | F28: 240 | G28: REGULAR | H28: =+F28*3% -> 7.2 | I28: =+F28+H28 -> 247.2 | J28: =+F28*12% -> 28.8 | K28: =+F28-J28 -> 211.2 | L28: =+F28*8% -> 19.2 | M28: =+F28-L28 -> 220.8 | N28: =+F28*25% -> 60 | O28: =+F28-N28 -> 180 | P28: 240 | Q28: 12 | R28: =+F28/Q28 -> 20
A29: PTFR02004 | B29: PAPANAX SALADO 110g | D29: CAJA | E29: UND | F29: 222 | G29: REGULAR | H29: =+F29*3% -> 6.66 | I29: =+F29+H29 -> 228.66 | J29: =+F29*12% -> 26.64 | K29: =+F29-J29 -> 195.36 | L29: =+F29*8% -> 17.76 | M29: =+F29-L29 -> 204.24 | N29: =+F29*25% -> 55.5 | O29: =+F29-N29 -> 166.5 | P29: 222 | Q29: 30 | R29: =+F29/Q29 -> 7.4
A30: PTFR02005 | B30: PAPANAX PICANTE 110g | D30: CAJA | E30: UND | F30: 222 | G30: REGULAR | H30: =+F30*3% -> 6.66 | I30: =+F30+H30 -> 228.66 | J30: =+F30*12% -> 26.64 | K30: =+F30-J30 -> 195.36 | L30: =+F30*8% -> 17.76 | M30: =+F30-L30 -> 204.24 | N30: =+F30*25% -> 55.5 | O30: =+F30-N30 -> 166.5 | P30: 222 | Q30: 30 | R30: =+F30/Q30 -> 7.4
A31: PTFR02001 | B31: PAPANAX SALADO 20g | D31: CAJA | E31: TIRA | F31: 240 | G31: REGULAR | H31: =+F31*3% -> 7.2 | I31: =+F31+H31 -> 247.2 | J31: =+F31*12% -> 28.8 | K31: =+F31-J31 -> 211.2 | L31: =+F31*8% -> 19.2 | M31: =+F31-L31 -> 220.8 | N31: =+F31*25% -> 60 | O31: =+F31-N31 -> 180 | P31: 240 | Q31: 12 | R31: =+F31/Q31 -> 20
... A34: PTTO01003 | B34: PIPANAX PICANTE 12X24X55g | D34: CAJA | E34: CAJA | F34: 408 | G34: REGULAR | H34: =+F34*3% -> 12.24 | I34: =+F34+H34 -> 420.24 | J34: =+F34*12% -> 48.96 | K34: =+F34-J34 -> 359.04 | L34: =+F34*8% -> 32.64 | M34: =+F34-L34 -> 375.36 | N34: =+F34*25% -> 102 | O34: =+F34-N34 -> 306 | P34: 408 | Q34: 12 | R34: =+F34/Q34 -> 34
A35: PTEX01009 | B35: PIPPOX MANTEQUILA 20g (21 BOLSAS/PAQUETE) | D35: JABA | E35: PAQ | F35: 57.5 | G35: REGULAR | H35: =+F35*3% -> 1.725 | I35: =+F35+H35 -> 59.225 | J35: =+F35*12% -> 6.9 | K35: =+F35-J35 -> 50.6 | L35: =+F35*8% -> 4.6 | M35: =+F35-L35 -> 52.9 | N35: 0 | O35: 0 | P35: 57.5 | Q35: 5 | R35: =+F35/Q35 -> 11.5
A36: PTFR03001 | B36: TOCINAX 35g EN TIRAS | D36: JABA | E36: TIRA | F36: 100 | G36: REGULAR | H36: =+F36*3% -> 3 | I36: =+F36+H36 -> 103 | J36: =+F36*12% -> 12 | K36: =+F36-J36 -> 88 | L36: =+F36*8% -> 8 | M36: =+F36-L36 -> 92 | N36: =+F36*25% -> 25 | O36: =+F36-N36 -> 75 | P36: 100 | Q36: 5 | R36: =+F36/Q36 -> 20
A37: PTFR03003 | B37: TOCINAX 120g | D37: JABA | E37: UND | F37: 148 | G37: REGULAR | H37: =+F37*3% -> 4.44 | I37: =+F37+H37 -> 152.44 | J37: =+F37*12% -> 17.76 | K37: =+F37-J37 -> 130.24 | L37: =+F37*8% -> 11.84 | M37: =+F37-L37 -> 136.16 | N37: =+F37*25% -> 37 | O37: =+F37-N37 -> 111 | P37: 148 | Q37: 20 | R37: =+F37/Q37 -> 7.4
B40: POLITICA: LOS PRECIOS DEBEN SER CON UN DECIMAL PARA REDONDEO
B41: SOLAMENTE EN EL CASO DE SUPERMECADO SE PODRA ELIGIR UNA UNIDAD DE MEDIDA SECUNDARIA
B42: PRESENTACIONES AL MOMENTO DEL REGISTRO DE LA VENTA PARA SUPERMERCADOS | K42: CAJA
B43: LA PRESENTACION 2 SOLO ES PARA VENTAS DE SUPERMERCADO | K43: JABA
K44: TIRA
K45: UNIDAD

Sheet RANGOS DE CLIENTES 
A1: Propuesta recomendada: 5 rangos de descuento por total de compra
I2: DESCUENTOS
A3: Rango | B3: Total de compra (Bs) | D3: Justificación | I3: PRODUCTOS REGULAR | J3: PRODUCTOS PROMOCIONALES
A4: 1 | B4: Hasta 4.999 | D4: Clientes ocasionales o pequeños, cuidas margen
A5: 2 | B5: 5.000 – 9.999 | D5: Gran mayoría de tus clientes | I5: 0.03 | J5: 0.05
A6: 3 | B6: 10.000 – 24.999 | D6: Clientes recurrentes y ya fidelizados | I6: 0.04 | J6: 0.06
A7: 4 | B7: 25.000 – 49.999 | D7: Compradores fuertes, incentivo claro | I7: 0.05 | J7: 0.07
A8: 5 | B8: Más de 50.000 | D8: Clientes clave / mayoristas reales | I8: 0.055 | J8: 0.075
B11: NOTA: LOS RANGOS SOLO DEBEN CONSIDERARDOS PARA:
D12: PRECIO VENTA MERCADOS
D13: PRECIO DE VENTA PROVINCIAS

Sheet Hoja5

Sheet Hoja4
B2: NACHONAX SALADO 45g tira | C2: PTFR01001 | D2: =+VLOOKUP(B2,'LISTADO DE PRECIOS'!$B$3:$D$37,3,FALSE) -> CAJA
B3: MEGABLON 14g BOLSA | C3: PTMA01002 | D3: =+VLOOKUP(B3,'LISTADO DE PRECIOS'!$B$3:$D$37,3,FALSE) -> CAJA
B4: MAESTRO QUESO 26g | C4: PTEX01001 | D4: =+VLOOKUP(B4,'LISTADO DE PRECIOS'!$B$3:$D$37,3,FALSE) -> #N/A
B5: BOOHOO CRUNCHY QUESO 40g (12 TIRAS/CAJA) | C5: PTEX01007 | D5: =+VLOOKUP(B5,'LISTADO DE PRECIOS'!$B$3:$D$37,3,FALSE) -> CAJA
B6: MAESTRO FUEGO 26g | C6: PTEX01002 | D6: =+VLOOKUP(B6,'LISTADO DE PRECIOS'!$B$3:$D$37,3,FALSE) -> #N/A
B7: BOOHOO PUFF PICANTE 30g (6 TIRAS/jABA) | C7: PTEX01005 | D7: =+VLOOKUP(B7,'LISTADO DE PRECIOS'!$B$3:$D$37,3,FALSE) -> JABA
B8: MAESTRO MANI 26g | C8: PTEX01003 | D8: =+VLOOKUP(B8,'LISTADO DE PRECIOS'!$B$3:$D$37,3,FALSE) -> #N/A
B9: MIX NAX 45G | C9: PTFR03002 | D9: =+VLOOKUP(B9,'LISTADO DE PRECIOS'!$B$3:$D$37,3,FALSE) -> CAJA
B10: PIPPOX MANTEQUILLA 20g (24 BOLSAS/PAQUETE) | C10: PTEX01006 | D10: =+VLOOKUP(B10,'LISTADO DE PRECIOS'!$B$3:$D$37,3,FALSE) -> #N/A
B11: BOOHOO QUESO 35g (UNIDADES SUELTAS) | C11: PTEX01008 | D11: =+VLOOKUP(B11,'LISTADO DE PRECIOS'!$B$3:$D$37,3,FALSE) -> #N/A
B12: BOOHOO QUESO 35g | C12: PTEX02001 | D12: =+VLOOKUP(B12,'LISTADO DE PRECIOS'!$B$3:$D$37,3,FALSE) -> JABA
B13: BOOHOO PUFF QUESO 120g (20 UNIDADES/JABA) | C13: PTEX01012 | D13: =+VLOOKUP(B13,'LISTADO DE PRECIOS'!$B$3:$D$37,3,FALSE) -> JABA
... B53: PIPANAX PICANTE 12X24X55g | C53: PTTO01003 | D53: =+VLOOKUP(B53,'LISTADO DE PRECIOS'!$B$3:$D$37,3,FALSE) -> CAJA
